{
  "variants": {
    "axis=x": [
      {
        "model": "biomesoplenty:block/umbran_log_horizontal",
        "x": 90,
        "y": 90
      },
      {
        "model": "biomesoplenty:block/umbran_log_knot_horizontal",
        "x": 90,
        "y": 90
      }
    ],
    "axis=y": [
      {
        "model": "biomesoplenty:block/umbran_log"
      },
      {
        "model": "biomesoplenty:block/umbran_log_knot"
      }
    ],
    "axis=z": [
      {
        "model": "biomesoplenty:block/umbran_log",
        "x": 90
      },
      {
        "model": "biomesoplenty:block/umbran_log_knot",
        "x": 90
      }
    ]
  }
}